[{"n":"AMD Ryzen 7 7700","iid":"ce58d360-25fc-43a6-8945-713d1fe3e5c9"},{"n":"AMD Ryzen 7 9700X","iid":"1959ad85-95d6-418d-913b-13dd9f112bc7"},{"n":"Intel Core Ultra 5 225F","iid":null},{"n":"AMD Ryzen 7 5700","iid":null},{"n":"AMD Ryzen 5 5600GT","iid":null},{"n":"Intel Core i9-12900K","iid":null},{"n":"AMD Ryzen 5 5600XT","iid":null},{"n":"AMD Ryzen 9 5900XT","iid":null},{"n":"AMD Ryzen 5 4500","iid":null},{"n":"Kingston FURY Beast RGB 16 GB","iid":null},{"n":"Intel Core i7-14700F","iid":null},{"n":"AMD Ryzen 7 8700F","iid":null},{"n":"AMD Ryzen 7 8700G","iid":null},{"n":"Intel Core i5-10400F","iid":null},{"n":"Intel Core i7-9700K","iid":null}]